sap_commerce_backoffice_icons/__init__.py
sap_commerce_backoffice_icons/backofficeIconConverter.py
sap_commerce_backoffice_icons-1.0.0.dist-info/entry_points.txt
sap_commerce_backoffice_icons-1.0.0.dist-info/LICENSE
sap_commerce_backoffice_icons-1.0.0.dist-info/WHEEL
sap_commerce_backoffice_icons-1.0.0.dist-info/METADATA
sap_commerce_backoffice_icons-1.0.0.dist-info/RECORD
