Metadata-Version: 2.1
Name: sap-commerce-backoffice-icons
Version: 1.0.0
Summary: Simple Tool to create explorer tree icons for the SAP Commerce Backoffice interface
Home-page: https://github.com/dev-jan/sap-commerce-backoffice-icons
License: MIT
Author: Jan Bucher
Author-email: jan@bucher.cloud
Requires-Python: >=3.7,<3.11
Classifier: Environment :: Console
Classifier: License :: OSI Approved :: MIT License
Classifier: Operating System :: OS Independent
Classifier: Programming Language :: Python :: 3
Classifier: Programming Language :: Python :: 3.7
Classifier: Programming Language :: Python :: 3.8
Classifier: Programming Language :: Python :: 3.9
Classifier: Topic :: Software Development
Requires-Dist: Pillow (>=8.4,<10.0)
Requires-Dist: argparse (>=1.4.0,<2.0.0)
Requires-Dist: numpy (>=1.21.3,<2.0.0)
Project-URL: Repository, https://github.com/dev-jan/sap-commerce-backoffice-icons
